facemorpher/__init__.py
facemorpher/aligner.py
facemorpher/averager.py
facemorpher/blender.py
facemorpher/locator.py
facemorpher/morpher.py
facemorpher/plotter.py
facemorpher/videoer.py
facemorpher/warper.py
facemorpher-5.2.1.data/data/readme/README.rst
facemorpher-5.2.1.dist-info/METADATA
facemorpher-5.2.1.dist-info/WHEEL
facemorpher-5.2.1.dist-info/entry_points.txt
facemorpher-5.2.1.dist-info/top_level.txt
facemorpher-5.2.1.dist-info/RECORD
