Metadata-Version: 2.1
Name: facemorpher
Version: 5.2.1
Summary: Warp, morph and average human faces!
Home-page: https://github.com/alyssaq/face_morpher
Author: Alyssa Quek
Author-email: alyssaquek@gmail.com
License: MIT
Keywords: face morphing,averaging,warping
Platform: UNKNOWN
Requires-Dist: docopt
Requires-Dist: numpy
Requires-Dist: scipy
Requires-Dist: matplotlib
Requires-Dist: stasm
